{
    "key": "group_67af64ae954c3",
    "title": "Block: Post Slider",
    "fields": [
        {
            "key": "field_67af64aece997",
            "label": "Eyebrow",
            "name": "eyebrow",
            "aria-label": "",
            "type": "text",
            "instructions": "",
            "required": 0,
            "conditional_logic": 0,
            "wrapper": {
                "width": "",
                "class": "",
                "id": ""
            },
            "default_value": "",
            "maxlength": "",
            "allow_in_bindings": 0,
            "placeholder": "",
            "prepend": "",
            "append": ""
        },
        {
            "key": "field_67af64bdce998",
            "label": "Heading",
            "name": "heading",
            "aria-label": "",
            "type": "textarea",
            "instructions": "",
            "required": 0,
            "conditional_logic": 0,
            "wrapper": {
                "width": "",
                "class": "",
                "id": ""
            },
            "default_value": "",
            "maxlength": "",
            "allow_in_bindings": 0,
            "rows": "",
            "placeholder": "",
            "new_lines": "br"
        },
        {
            "key": "field_67af64d7ce999",
            "label": "Subheading",
            "name": "subheading",
            "aria-label": "",
            "type": "wysiwyg",
            "instructions": "",
            "required": 0,
            "conditional_logic": 0,
            "wrapper": {
                "width": "",
                "class": "",
                "id": ""
            },
            "default_value": "",
            "allow_in_bindings": 0,
            "tabs": "all",
            "toolbar": "full",
            "media_upload": 1,
            "delay": 0
        },
        {
            "key": "field_67af6527ce99b",
            "label": "Button",
            "name": "button",
            "aria-label": "",
            "type": "link",
            "instructions": "",
            "required": 0,
            "conditional_logic": 0,
            "wrapper": {
                "width": "",
                "class": "",
                "id": ""
            },
            "return_format": "array",
            "allow_in_bindings": 0
        },
        {
            "key": "field_67af64e7ce99a",
            "label": "Items",
            "name": "items",
            "aria-label": "",
            "type": "post_object",
            "instructions": "",
            "required": 0,
            "conditional_logic": 0,
            "wrapper": {
                "width": "",
                "class": "",
                "id": ""
            },
            "post_type": "",
            "post_status": [
                "publish"
            ],
            "taxonomy": "",
            "return_format": "id",
            "multiple": 1,
            "allow_null": 0,
            "allow_in_bindings": 0,
            "bidirectional": 0,
            "ui": 1,
            "bidirectional_target": []
        },
        {
            "key": "field_689cde852ea78",
            "label": "Internal Page",
            "name": "internal_page",
            "aria-label": "",
            "type": "true_false",
            "instructions": "",
            "required": 0,
            "conditional_logic": 0,
            "wrapper": {
                "width": "",
                "class": "",
                "id": ""
            },
            "message": "",
            "default_value": 0,
            "allow_in_bindings": 0,
            "ui_on_text": "",
            "ui_off_text": "",
            "ui": 1
        }
    ],
    "location": [
        [
            {
                "param": "block",
                "operator": "==",
                "value": "acf\/post-slider"
            }
        ]
    ],
    "menu_order": 0,
    "position": "normal",
    "style": "default",
    "label_placement": "top",
    "instruction_placement": "label",
    "hide_on_screen": "",
    "active": true,
    "description": "",
    "show_in_rest": 0,
    "modified": 1755111065
}
